WebRender/__init__.py
WebRender/custom_execution.py
WebRender/logger.py
WebRender/site.py
WebRender/youtube.py
webrender-0.0.8.dist-info/LICENSE
webrender-0.0.8.dist-info/METADATA
webrender-0.0.8.dist-info/WHEEL
webrender-0.0.8.dist-info/top_level.txt
webrender-0.0.8.dist-info/RECORD
