Metadata-Version: 2.1
Name: WebRender
Version: 0.0.8
Summary: A small web render python package
Home-page: https://github.com/ranak8811/Web-Render-PyPi-Package
Author: ranak8811
Author-email: ranakrphone@gmail.com
License: MIT
Project-URL: Bug Tracker, https://github.com/ranak8811/Web-Render-PyPi-Package/issues
Classifier: Programming Language :: Python :: 3.8
Classifier: Programming Language :: Python :: 3.9
Classifier: Programming Language :: Python :: 3.10
Classifier: Programming Language :: Python :: 3.11
Classifier: Operating System :: OS Independent
Requires-Python: >=3.8
License-File: LICENSE
Requires-Dist: ensure==1.0.2
Requires-Dist: py-youtube==1.1.7
Provides-Extra: testing
Requires-Dist: pytest>=7.1.3; extra == "testing"
Requires-Dist: mypy>=0.971; extra == "testing"
Requires-Dist: flake8>=5.0.4; extra == "testing"
Requires-Dist: tox>=3.25.1; extra == "testing"
